openevolve/__init__.py
openevolve/_version.py
openevolve/api.py
openevolve/cli.py
openevolve/config.py
openevolve/controller.py
openevolve/database.py
openevolve/embedding.py
openevolve/evaluation_result.py
openevolve/evaluator.py
openevolve/evolution_trace.py
openevolve/iteration.py
openevolve/novelty_judge.py
openevolve/process_parallel.py
openevolve/test_regional_endpoint.py
openevolve/llm/__init__.py
openevolve/llm/base.py
openevolve/llm/ensemble.py
openevolve/llm/openai.py
openevolve/prompt/__init__.py
openevolve/prompt/sampler.py
openevolve/prompt/templates.py
openevolve/prompts/defaults/diff_user.txt
openevolve/prompts/defaults/evaluation.txt
openevolve/prompts/defaults/evaluator_system_message.txt
openevolve/prompts/defaults/evolution_history.txt
openevolve/prompts/defaults/fragments.json
openevolve/prompts/defaults/full_rewrite_user.txt
openevolve/prompts/defaults/inspiration_program.txt
openevolve/prompts/defaults/inspirations_section.txt
openevolve/prompts/defaults/previous_attempt.txt
openevolve/prompts/defaults/system_message.txt
openevolve/prompts/defaults/top_program.txt
openevolve/utils/__init__.py
openevolve/utils/async_utils.py
openevolve/utils/code_utils.py
openevolve/utils/format_utils.py
openevolve/utils/metrics_utils.py
openevolve/utils/trace_export_utils.py
openevolve-0.2.24.dist-info/licenses/LICENSE
openevolve-0.2.24.dist-info/METADATA
openevolve-0.2.24.dist-info/WHEEL
openevolve-0.2.24.dist-info/entry_points.txt
openevolve-0.2.24.dist-info/top_level.txt
openevolve-0.2.24.dist-info/RECORD
